scripts/__init__.py
scripts/tfplan.py
tests/__init__.py
tests/test_planner_hindsight.py
tests/test_planner_straightline.py
tests/test_planner_tensorplan.py
tests/test_policy.py
tests/test_simulation_deterministic.py
tests/test_simulation_stochastic.py
tests/test_stochastic_utils.py
tfplan/__init__.py
tfplan/version.py
tfplan/planners/__init__.py
tfplan/planners/planner.py
tfplan/planners/deterministic/__init__.py
tfplan/planners/deterministic/simulation.py
tfplan/planners/deterministic/tensorplan.py
tfplan/planners/deterministic/utils.py
tfplan/planners/stochastic/__init__.py
tfplan/planners/stochastic/hindsight.py
tfplan/planners/stochastic/simulation.py
tfplan/planners/stochastic/straightline.py
tfplan/planners/stochastic/utils.py
tfplan/train/__init__.py
tfplan/train/optimizer.py
tfplan/train/policy.py
tfplan/train/scheduler.py
tf_plan-0.7.5.dist-info/LICENSE
tf_plan-0.7.5.dist-info/METADATA
tf_plan-0.7.5.dist-info/WHEEL
tf_plan-0.7.5.dist-info/entry_points.txt
tf_plan-0.7.5.dist-info/top_level.txt
tf_plan-0.7.5.dist-info/RECORD
