Metadata-Version: 2.1
Name: tf-plan
Version: 0.7.5
Summary: Planning through backpropagation using TensorFlow.
Home-page: https://github.com/thiagopbueno/tf-plan
Author: Thiago P. Bueno
Author-email: thiago.pbueno@gmail.com
License: GNU General Public License v3.0
Keywords: planning,tensorflow,rddl,mdp
Platform: UNKNOWN
Classifier: Development Status :: 3 - Alpha
Classifier: Environment :: Console
Classifier: Intended Audience :: Science/Research
Classifier: License :: OSI Approved :: GNU General Public License v3 (GPLv3)
Classifier: Natural Language :: English
Classifier: Operating System :: OS Independent
Classifier: Programming Language :: Python :: 3.6
Classifier: Topic :: Scientific/Engineering :: Artificial Intelligence
Requires-Python: >=3.5
Requires-Dist: Click
Requires-Dist: tqdm
Requires-Dist: psutil
Requires-Dist: tensorflow-cpu (<2.0)
Requires-Dist: rddlgym
Requires-Dist: rddl2tf
Requires-Dist: tuneconfig
